<?xml version="1.0" encoding="UTF-8"?>
<odoo>
    <template id="assets_backend" inherit_id="web.assets_backend">
        <xpath expr="." position="inside">
            <!-- Link to your JavaScript and XML template files -->
            <link rel="stylesheet" type="text/scss" href="/estate/static/src/scss/color_pill.scss"/>
            <!-- <link rel="stylesheet" type="text/scss" href="/estate/static/src/scss/mm_yyyy.scss"/> -->
            <script  type="text/javascript" src="/estate/static/src/js/color_pill_widget.js"></script>
            <script  type="text/javascript" src="/estate/static/src/js/mm_yyyy_widget.js"></script>
            <script  type="text/javascript" src="/estate/static/src/js/button_click_me_widget.js"></script>
            
        </xpath>
    </template>
</odoo>
